xl_database/__init__.py
xl_database/mixins.py
xl_database/model.py
xl_database/utils/time.py
xl_database-0.9.3.dist-info/METADATA
xl_database-0.9.3.dist-info/WHEEL
xl_database-0.9.3.dist-info/licenses/LICENSE
xl_database-0.9.3.dist-info/RECORD
