Metadata-Version: 2.4
Name: xl-database
Version: 0.9.3
Summary: xilong database library
Project-URL: Homepage, https://git.xilonglab.com/xilong/zdatabase
Project-URL: Bug Tracker, https://git.xilonglab.com/xilong/zdatabase/issues
Author-email: xilong <xilonglab@163.com>
License-File: LICENSE
Classifier: License :: OSI Approved :: MIT License
Classifier: Operating System :: OS Independent
Classifier: Programming Language :: Python :: 3
Requires-Python: >=3.7
Requires-Dist: arrow==0.17.0
Requires-Dist: flask-sqlalchemy==2.5.1
Requires-Dist: jsonschema==4.17.3
Requires-Dist: pymysql==1.0.2
Requires-Dist: sqlalchemy==1.4.39
